fiktivna/__init__.py
fiktivna/__main__.py
fiktivna/functions.py
fiktivna-1.0.4.dist-info/METADATA
fiktivna-1.0.4.dist-info/WHEEL
fiktivna-1.0.4.dist-info/top_level.txt
fiktivna-1.0.4.dist-info/RECORD
